[{"line":1,"elements":[{"line":3,"name":"","description":"","type":"background","keyword":"Background","steps":[{"name":"url 'https:\/\/simple-grocery-store-api.glitch.me'","result":{"duration":1144300,"status":"passed"},"match":{"location":"karate","arguments":[]},"keyword":"Given","line":4,"doc_string":{"content_type":"","value":"00:47:57.133 karate.env system property was: null \n","line":4}}]},{"start_timestamp":"2024-05-15T19:17:57.013Z","line":6,"name":"To automate","description":"","id":"to-automate","type":"scenario","keyword":"Scenario","steps":[{"name":"call read(\"classpath:com\/api\/automation\/GetStatus\/GetStatus.feature\")","result":{"duration":2374281900,"status":"passed"},"match":{"location":"karate","arguments":[]},"comments":["#\tSTATUS"],"keyword":"Given","line":8},{"name":"com\/api\/automation\/GetStatus\/GetStatus.feature","result":{"duration":0,"status":"passed"},"match":{"location":"karate","arguments":[]},"keyword":"","line":8},{"name":"url 'http:\/\/simple-grocery-store-api.online'","result":{"duration":2020299,"status":"passed"},"match":{"location":"karate","arguments":[]},"keyword":"> Given","line":4},{"name":"path '\/status'","result":{"duration":620201,"status":"passed"},"match":{"location":"karate","arguments":[]},"keyword":"> Given","line":7},{"name":"method get","result":{"duration":2350740800,"status":"passed"},"match":{"location":"karate","arguments":[]},"keyword":"> When","line":8,"doc_string":{"content_type":"","value":"00:47:57.618 request:\n1 > GET http:\/\/simple-grocery-store-api.online\/status\n1 > Host: simple-grocery-store-api.online\n1 > Connection: Keep-Alive\n1 > User-Agent: Apache-HttpClient\/4.5.14 (Java\/11.0.22)\n1 > Accept-Encoding: gzip,deflate\n\n\n00:47:59.538 response time in milliseconds: 1919\n1 < 200\n1 < server: Fly\/d5207058 (2024-05-13)\n1 < fly-request-id: 01HXYV171VJ5BKRJ3Q58S4JKSZ-bom\n1 < date: Wed, 15 May 2024 19:17:59 GMT\n1 < content-type: application\/json; charset=utf-8\n1 < x-powered-by: Express\n1 < etag: W\/\"f-RQ8OySFd+KR+AvtJ7qImjtT0D\/0\"\n1 < transfer-encoding: chunked\n1 < via: 1.1 fly.io\n{\"status\":\"UP\"}\n\n","line":8}},{"name":"status 200","result":{"duration":14000,"status":"passed"},"match":{"location":"karate","arguments":[]},"keyword":"> Then","line":9},{"name":"match response.status == 'UP'","result":{"duration":2534599,"status":"passed"},"match":{"location":"karate","arguments":[]},"keyword":"> And","line":10},{"name":"call read(\"classpath:com\/api\/automation\/Product\/getAllProducts.feature\")","result":{"duration":1475731399,"status":"passed"},"match":{"location":"karate","arguments":[]},"comments":["# PRODUCTS"],"keyword":"And","line":10},{"name":"com\/api\/automation\/Product\/getAllProducts.feature","result":{"duration":0,"status":"passed"},"match":{"location":"karate","arguments":[]},"keyword":"","line":10},{"name":"url 'http:\/\/simple-grocery-store-api.online'","result":{"duration":215700,"status":"passed"},"match":{"location":"karate","arguments":[]},"keyword":"> Given","line":4},{"name":"path '\/products'","result":{"duration":526900,"status":"passed"},"match":{"location":"karate","arguments":[]},"keyword":"> Given","line":7},{"name":"method get","result":{"duration":1410473600,"status":"passed"},"match":{"location":"karate","arguments":[]},"keyword":"> When","line":8,"doc_string":{"content_type":"","value":"00:47:59.570 request:\n1 > GET http:\/\/simple-grocery-store-api.online\/products\n1 > Host: simple-grocery-store-api.online\n1 > Connection: Keep-Alive\n1 > User-Agent: Apache-HttpClient\/4.5.14 (Java\/11.0.22)\n1 > Accept-Encoding: gzip,deflate\n\n\n00:48:00.977 response time in milliseconds: 1406\n1 < 200\n1 < server: Fly\/d5207058 (2024-05-13)\n1 < fly-request-id: 01HXYV18XWCNF5DAS4SHVN4DN2-bom\n1 < date: Wed, 15 May 2024 19:18:00 GMT\n1 < content-type: application\/json; charset=utf-8\n1 < x-powered-by: Express\n1 < etag: W\/\"6b4-RVZTrjCoC03tQFslV\/oF2zXZ8Wo\"\n1 < transfer-encoding: chunked\n1 < via: 1.1 fly.io\n[{\"id\":4643,\"category\":\"coffee\",\"name\":\"Starbucks Coffee Variety Pack, 100% Arabica\",\"inStock\":true},{\"id\":4646,\"category\":\"coffee\",\"name\":\"Ethical Bean Medium Dark Roast, Espresso\",\"inStock\":true},{\"id\":4641,\"category\":\"coffee\",\"name\":\"Don Francisco Colombia Supremo Medium Roast\",\"inStock\":true},{\"id\":1225,\"category\":\"fresh-produce\",\"name\":\"1\/2 in. Brushless Hammer Drill\",\"inStock\":true},{\"id\":3674,\"category\":\"fresh-produce\",\"name\":\"20V Max Cordless Drill Combo Kit\",\"inStock\":true},{\"id\":2585,\"category\":\"fresh-produce\",\"name\":\"Green Cabbage Organic\",\"inStock\":true},{\"id\":5851,\"category\":\"fresh-produce\",\"name\":\"Cucumber Organic\",\"inStock\":false},{\"id\":8739,\"category\":\"fresh-produce\",\"name\":\"Fresh Spinach Organic\",\"inStock\":true},{\"id\":2177,\"category\":\"meat-seafood\",\"name\":\"Cosco Three Step Steel Platform\",\"inStock\":true},{\"id\":1709,\"category\":\"meat-seafood\",\"name\":\"Beef Choice Angus Ribeye Steak\",\"inStock\":true},{\"id\":1709,\"category\":\"meat-seafood\",\"name\":\"Angus Steak Burgers\",\"inStock\":true},{\"id\":7395,\"category\":\"meat-seafood\",\"name\":\"Boneless Skinless Chicken Breasts\",\"inStock\":true},{\"id\":8554,\"category\":\"candy\",\"name\":\"Kinder Joy Eggs\",\"inStock\":true},{\"id\":6483,\"category\":\"candy\",\"name\":\"Cadbury Milk Chocolate\",\"inStock\":true},{\"id\":5774,\"category\":\"candy\",\"name\":\"HERSHEY'S, Milk Chocolate Almond\",\"inStock\":true},{\"id\":8753,\"category\":\"dairy\",\"name\":\"Reduced Fat Milk\",\"inStock\":true},{\"id\":9482,\"category\":\"dairy\",\"name\":\"Whole Milk\",\"inStock\":true},{\"id\":5477,\"category\":\"dairy\",\"name\":\"Cream Cheese\",\"inStock\":true},{\"id\":5478,\"category\":\"dairy\",\"name\":\"Low Fat Vanilla Yogurt\",\"inStock\":true},{\"id\":4875,\"category\":\"bread-bakery\",\"name\":\"2800 Watt Inverter Generator\",\"inStock\":true}]\n\n","line":8}},{"name":"status 200","result":{"duration":7999,"status":"passed"},"match":{"location":"karate","arguments":[]},"keyword":"> Then","line":9},{"name":"print response","result":{"duration":3784401,"status":"passed"},"match":{"location":"karate","arguments":[]},"keyword":"> And","line":10,"doc_string":{"content_type":"","value":"00:48:00.982 [print] [\n  {\n    \"id\": 4643,\n    \"category\": \"coffee\",\n    \"name\": \"Starbucks Coffee Variety Pack, 100% Arabica\",\n    \"inStock\": true\n  },\n  {\n    \"id\": 4646,\n    \"category\": \"coffee\",\n    \"name\": \"Ethical Bean Medium Dark Roast, Espresso\",\n    \"inStock\": true\n  },\n  {\n    \"id\": 4641,\n    \"category\": \"coffee\",\n    \"name\": \"Don Francisco Colombia Supremo Medium Roast\",\n    \"inStock\": true\n  },\n  {\n    \"id\": 1225,\n    \"category\": \"fresh-produce\",\n    \"name\": \"1\/2 in. Brushless Hammer Drill\",\n    \"inStock\": true\n  },\n  {\n    \"id\": 3674,\n    \"category\": \"fresh-produce\",\n    \"name\": \"20V Max Cordless Drill Combo Kit\",\n    \"inStock\": true\n  },\n  {\n    \"id\": 2585,\n    \"category\": \"fresh-produce\",\n    \"name\": \"Green Cabbage Organic\",\n    \"inStock\": true\n  },\n  {\n    \"id\": 5851,\n    \"category\": \"fresh-produce\",\n    \"name\": \"Cucumber Organic\",\n    \"inStock\": false\n  },\n  {\n    \"id\": 8739,\n    \"category\": \"fresh-produce\",\n    \"name\": \"Fresh Spinach Organic\",\n    \"inStock\": true\n  },\n  {\n    \"id\": 2177,\n    \"category\": \"meat-seafood\",\n    \"name\": \"Cosco Three Step Steel Platform\",\n    \"inStock\": true\n  },\n  {\n    \"id\": 1709,\n    \"category\": \"meat-seafood\",\n    \"name\": \"Beef Choice Angus Ribeye Steak\",\n    \"inStock\": true\n  },\n  {\n    \"id\": 1709,\n    \"category\": \"meat-seafood\",\n    \"name\": \"Angus Steak Burgers\",\n    \"inStock\": true\n  },\n  {\n    \"id\": 7395,\n    \"category\": \"meat-seafood\",\n    \"name\": \"Boneless Skinless Chicken Breasts\",\n    \"inStock\": true\n  },\n  {\n    \"id\": 8554,\n    \"category\": \"candy\",\n    \"name\": \"Kinder Joy Eggs\",\n    \"inStock\": true\n  },\n  {\n    \"id\": 6483,\n    \"category\": \"candy\",\n    \"name\": \"Cadbury Milk Chocolate\",\n    \"inStock\": true\n  },\n  {\n    \"id\": 5774,\n    \"category\": \"candy\",\n    \"name\": \"HERSHEY'S, Milk Chocolate Almond\",\n    \"inStock\": true\n  },\n  {\n    \"id\": 8753,\n    \"category\": \"dairy\",\n    \"name\": \"Reduced Fat Milk\",\n    \"inStock\": true\n  },\n  {\n    \"id\": 9482,\n    \"category\": \"dairy\",\n    \"name\": \"Whole Milk\",\n    \"inStock\": true\n  },\n  {\n    \"id\": 5477,\n    \"category\": \"dairy\",\n    \"name\": \"Cream Cheese\",\n    \"inStock\": true\n  },\n  {\n    \"id\": 5478,\n    \"category\": \"dairy\",\n    \"name\": \"Low Fat Vanilla Yogurt\",\n    \"inStock\": true\n  },\n  {\n    \"id\": 4875,\n    \"category\": \"bread-bakery\",\n    \"name\": \"2800 Watt Inverter Generator\",\n    \"inStock\": true\n  }\n]\n \n","line":10}},{"name":"match each $ contains { 'id': '#number', 'category': '#string', 'name': '#string', 'inStock': '#boolean' }","result":{"duration":44275900,"status":"passed"},"match":{"location":"karate","arguments":[]},"keyword":"> And","line":11},{"name":"call read(\"classpath:com\/api\/automation\/Product\/getSingleProduct.feature\")","result":{"duration":1281115099,"status":"passed"},"match":{"location":"karate","arguments":[]},"keyword":"And","line":11},{"name":"com\/api\/automation\/Product\/getSingleProduct.feature","result":{"duration":0,"status":"passed"},"match":{"location":"karate","arguments":[]},"keyword":"","line":11},{"name":"url 'http:\/\/simple-grocery-store-api.online'","result":{"duration":602700,"status":"passed"},"match":{"location":"karate","arguments":[]},"keyword":"> Given","line":4},{"name":"path '\/products\/4643'","result":{"duration":355300,"status":"passed"},"match":{"location":"karate","arguments":[]},"keyword":"> Given","line":20},{"name":"method GET","result":{"duration":444800000,"status":"passed"},"match":{"location":"karate","arguments":[]},"keyword":"> When","line":21,"doc_string":{"content_type":"","value":"00:48:01.043 request:\n1 > GET http:\/\/simple-grocery-store-api.online\/products\/4643\n1 > Host: simple-grocery-store-api.online\n1 > Connection: Keep-Alive\n1 > User-Agent: Apache-HttpClient\/4.5.14 (Java\/11.0.22)\n1 > Accept-Encoding: gzip,deflate\n\n\n00:48:01.485 response time in milliseconds: 441\n1 < 200\n1 < server: Fly\/d5207058 (2024-05-13)\n1 < fly-request-id: 01HXYV1ABXJV744XJV7RY9G5PZ-bom\n1 < date: Wed, 15 May 2024 19:18:01 GMT\n1 < content-type: application\/json; charset=utf-8\n1 < x-powered-by: Express\n1 < etag: W\/\"9f-HOV8MpLmQj4WLcZExQr2z\/Z8zWc\"\n1 < transfer-encoding: chunked\n1 < via: 1.1 fly.io\n{\"id\":4643,\"category\":\"coffee\",\"name\":\"Starbucks Coffee Variety Pack, 100% Arabica\",\"manufacturer\":\"Starbucks\",\"price\":40.91,\"current-stock\":14,\"inStock\":true}\n\n","line":21}},{"name":"status 200","result":{"duration":10900,"status":"passed"},"match":{"location":"karate","arguments":[]},"keyword":"> Then","line":22},{"name":"match response == { id: '#number',category : '#string', name: '#string',manufacturer:'#string', price: '#number',current-stock:'#number',inStock:'#boolean'}","result":{"duration":1225900,"status":"passed"},"match":{"location":"karate","arguments":[]},"keyword":"> And","line":23},{"name":"url 'http:\/\/simple-grocery-store-api.online'","result":{"duration":180400,"status":"passed"},"match":{"location":"karate","arguments":[]},"keyword":"> Given","line":4},{"name":"path '\/products\/2585'","result":{"duration":465700,"status":"passed"},"match":{"location":"karate","arguments":[]},"keyword":"> Given","line":20},{"name":"method GET","result":{"duration":401353900,"status":"passed"},"match":{"location":"karate","arguments":[]},"keyword":"> When","line":21,"doc_string":{"content_type":"","value":"00:48:01.498 request:\n1 > GET http:\/\/simple-grocery-store-api.online\/products\/2585\n1 > Host: simple-grocery-store-api.online\n1 > Connection: Keep-Alive\n1 > User-Agent: Apache-HttpClient\/4.5.14 (Java\/11.0.22)\n1 > Accept-Encoding: gzip,deflate\n\n\n00:48:01.896 response time in milliseconds: 398\n1 < 200\n1 < server: Fly\/d5207058 (2024-05-13)\n1 < fly-request-id: 01HXYV1AT4JH4YFYKX11GPFHQ5-bom\n1 < date: Wed, 15 May 2024 19:18:01 GMT\n1 < content-type: application\/json; charset=utf-8\n1 < x-powered-by: Express\n1 < etag: W\/\"9d-8LLankJoMT59pax+F+OJXdFG\/Xg\"\n1 < transfer-encoding: chunked\n1 < via: 1.1 fly.io\n{\"id\":2585,\"category\":\"fresh-produce\",\"name\":\"Green Cabbage Organic\",\"manufacturer\":\"Jack&Mary Organic Farms\",\"price\":3.02,\"current-stock\":30,\"inStock\":true}\n\n","line":21}},{"name":"status 200","result":{"duration":4600,"status":"passed"},"match":{"location":"karate","arguments":[]},"keyword":"> Then","line":22},{"name":"match response == { id: '#number',category : '#string', name: '#string',manufacturer:'#string', price: '#number',current-stock:'#number',inStock:'#boolean'}","result":{"duration":556000,"status":"passed"},"match":{"location":"karate","arguments":[]},"keyword":"> And","line":23},{"name":"url 'http:\/\/simple-grocery-store-api.online'","result":{"duration":356100,"status":"passed"},"match":{"location":"karate","arguments":[]},"keyword":"> Given","line":4},{"name":"path '\/products\/4641'","result":{"duration":471099,"status":"passed"},"match":{"location":"karate","arguments":[]},"keyword":"> Given","line":20},{"name":"method GET","result":{"duration":403036900,"status":"passed"},"match":{"location":"karate","arguments":[]},"keyword":"> When","line":21,"doc_string":{"content_type":"","value":"00:48:01.905 request:\n1 > GET http:\/\/simple-grocery-store-api.online\/products\/4641\n1 > Host: simple-grocery-store-api.online\n1 > Connection: Keep-Alive\n1 > User-Agent: Apache-HttpClient\/4.5.14 (Java\/11.0.22)\n1 > Accept-Encoding: gzip,deflate\n\n\n00:48:02.305 response time in milliseconds: 399\n1 < 200\n1 < server: Fly\/d5207058 (2024-05-13)\n1 < fly-request-id: 01HXYV1B6F949V93VKVZT4GNJ5-bom\n1 < date: Wed, 15 May 2024 19:18:01 GMT\n1 < content-type: application\/json; charset=utf-8\n1 < x-powered-by: Express\n1 < etag: W\/\"a2-hfgHV3lf1DHKv77B2hBDPeUZ7dg\"\n1 < transfer-encoding: chunked\n1 < via: 1.1 fly.io\n{\"id\":4641,\"category\":\"coffee\",\"name\":\"Don Francisco Colombia Supremo Medium Roast\",\"manufacturer\":\"Don Francisco\",\"price\":9.76,\"current-stock\":15,\"inStock\":true}\n\n","line":21}},{"name":"status 200","result":{"duration":9000,"status":"passed"},"match":{"location":"karate","arguments":[]},"keyword":"> Then","line":22},{"name":"match response == { id: '#number',category : '#string', name: '#string',manufacturer:'#string', price: '#number',current-stock:'#number',inStock:'#boolean'}","result":{"duration":602701,"status":"passed"},"match":{"location":"karate","arguments":[]},"keyword":"> And","line":23},{"name":"call read(\"classpath:com\/api\/automation\/Cart\/createNewCart.feature\")","result":{"duration":615410200,"status":"passed"},"match":{"location":"karate","arguments":[]},"comments":["# CART"],"keyword":"And","line":13},{"name":"com\/api\/automation\/Cart\/createNewCart.feature","result":{"duration":0,"status":"passed"},"match":{"location":"karate","arguments":[]},"keyword":"","line":13},{"name":"url 'http:\/\/simple-grocery-store-api.online'","result":{"duration":154201,"status":"passed"},"match":{"location":"karate","arguments":[]},"keyword":"> Given","line":4},{"name":"path '\/carts'","result":{"duration":478701,"status":"passed"},"match":{"location":"karate","arguments":[]},"keyword":"> Given","line":22},{"name":"method post","result":{"duration":602991900,"status":"passed"},"match":{"location":"karate","arguments":[]},"keyword":"> When","line":23,"doc_string":{"content_type":"","value":"00:48:02.318 request:\n1 > POST http:\/\/simple-grocery-store-api.online\/carts\n1 > Host: simple-grocery-store-api.online\n1 > Connection: Keep-Alive\n1 > User-Agent: Apache-HttpClient\/4.5.14 (Java\/11.0.22)\n1 > Accept-Encoding: gzip,deflate\n\n\n00:48:02.918 response time in milliseconds: 599\n1 < 201\n1 < server: Fly\/d5207058 (2024-05-13)\n1 < fly-request-id: 01HXYV1BKDK1S11YJDS5YXNG92-bom\n1 < date: Wed, 15 May 2024 19:18:02 GMT\n1 < content-type: application\/json; charset=utf-8\n1 < x-powered-by: Express\n1 < etag: W\/\"31-jC320uMzwppDTv5AXFHqbVuSMv0\"\n1 < transfer-encoding: chunked\n1 < via: 1.1 fly.io\n{\"created\":true,\"cartId\":\"RlcRT5nbQ2_EsOWkDEmeD\"}\n\n","line":23}},{"name":"status 201","result":{"duration":7600,"status":"passed"},"match":{"location":"karate","arguments":[]},"keyword":"> Then","line":24},{"name":"match response.created == true","result":{"duration":999399,"status":"passed"},"match":{"location":"karate","arguments":[]},"keyword":"> And","line":25},{"name":"def cartId = response.cartId","result":{"duration":920800,"status":"passed"},"match":{"location":"karate","arguments":[]},"keyword":"> And","line":26},{"name":"karate.write(cartId, 'cartId.txt')","result":{"duration":2048000,"status":"passed"},"match":{"location":"karate","arguments":[]},"keyword":"> And","line":27,"doc_string":{"content_type":"","value":"00:48:02.923 write to file: target\\cartId.txt\n","line":27}},{"name":"call read(\"classpath:com\/api\/automation\/Cart\/getCart.feature\")","result":{"duration":18306200,"status":"passed"},"match":{"location":"karate","arguments":[]},"keyword":"And","line":14},{"name":"com\/api\/automation\/Cart\/getCart.feature","result":{"duration":0,"status":"passed"},"match":{"location":"karate","arguments":[]},"keyword":"","line":14},{"name":"url 'http:\/\/simple-grocery-store-api.online'","result":{"duration":203900,"status":"passed"},"match":{"location":"karate","arguments":[]},"keyword":"> Given","line":4},{"name":"def File = Java.type('java.io.File')","result":{"duration":938000,"status":"passed"},"match":{"location":"karate","arguments":[]},"keyword":"> *","line":32},{"name":"def Scanner = Java.type('java.util.Scanner')","result":{"duration":938600,"status":"passed"},"match":{"location":"karate","arguments":[]},"keyword":"> *","line":33},{"name":"def path = 'C:\/Users\/HarshvardhanNigaveka\/eclipse-workspace\/Grocery_karateFramework\/target\/CartId.txt'","result":{"duration":434100,"status":"passed"},"match":{"location":"karate","arguments":[]},"keyword":"> *","line":34},{"name":"def file = new File(path)","result":{"duration":796701,"status":"passed"},"match":{"location":"karate","arguments":[]},"keyword":"> *","line":35},{"name":"def scanner = new Scanner(file)","result":{"duration":1532900,"status":"passed"},"match":{"location":"karate","arguments":[]},"keyword":"> *","line":36},{"name":"def cartId = scanner.useDelimiter('\\\\Z').next()","result":{"duration":2026901,"status":"passed"},"match":{"location":"karate","arguments":[]},"keyword":"> *","line":37},{"name":"scanner.close()","result":{"duration":1015500,"status":"passed"},"match":{"location":"karate","arguments":[]},"keyword":"> *","line":38},{"name":"print 'Cart ID in get cart:', cartId","result":{"duration":1429500,"status":"passed"},"match":{"location":"karate","arguments":[]},"keyword":"> *","line":39,"doc_string":{"content_type":"","value":"00:48:02.941 [print] Cart ID in get cart: RlcRT5nbQ2_EsOWkDEmeD \n","line":39}},{"name":"call read(\"classpath:com\/api\/automation\/Cart\/addItemsToCart.feature\")","result":{"duration":2025590001,"status":"passed"},"match":{"location":"karate","arguments":[]},"keyword":"And","line":15},{"name":"com\/api\/automation\/Cart\/addItemsToCart.feature","result":{"duration":0,"status":"passed"},"match":{"location":"karate","arguments":[]},"keyword":"","line":15},{"name":"url 'http:\/\/simple-grocery-store-api.online'","result":{"duration":227100,"status":"passed"},"match":{"location":"karate","arguments":[]},"keyword":"> Given","line":4},{"name":"def File = Java.type('java.io.File')","result":{"duration":761901,"status":"passed"},"match":{"location":"karate","arguments":[]},"keyword":"> *","line":5},{"name":"def Scanner = Java.type('java.util.Scanner')","result":{"duration":624701,"status":"passed"},"match":{"location":"karate","arguments":[]},"keyword":"> *","line":6},{"name":"def path = 'C:\/Users\/HarshvardhanNigaveka\/eclipse-workspace\/Grocery_karateFramework\/target\/CartId.txt'","result":{"duration":673599,"status":"passed"},"match":{"location":"karate","arguments":[]},"keyword":"> *","line":7},{"name":"def file = new File(path)","result":{"duration":897399,"status":"passed"},"match":{"location":"karate","arguments":[]},"keyword":"> *","line":8},{"name":"def scanner = new Scanner(file)","result":{"duration":1517300,"status":"passed"},"match":{"location":"karate","arguments":[]},"keyword":"> *","line":9},{"name":"def cartId = scanner.useDelimiter('\\\\Z').next()","result":{"duration":1016900,"status":"passed"},"match":{"location":"karate","arguments":[]},"keyword":"> *","line":10},{"name":"scanner.close()","result":{"duration":381200,"status":"passed"},"match":{"location":"karate","arguments":[]},"keyword":"> *","line":11},{"name":"path '\/carts\/' + cartId + '\/items'","result":{"duration":739699,"status":"passed"},"match":{"location":"karate","arguments":[]},"keyword":"> Given","line":35},{"name":"request { \"productId\": 4641, \"quantity\": 1 }","result":{"duration":155000,"status":"passed"},"match":{"location":"karate","arguments":[]},"keyword":"> And","line":36},{"name":"headers {Accept :\"application\/json\",Content-type : \"application\/json\"}","result":{"duration":111600,"status":"passed"},"match":{"location":"karate","arguments":[]},"keyword":"> And","line":37},{"name":"method POST","result":{"duration":670858200,"status":"passed"},"match":{"location":"karate","arguments":[]},"keyword":"> When","line":38,"doc_string":{"content_type":"","value":"00:48:02.967 request:\n1 > POST http:\/\/simple-grocery-store-api.online\/carts\/RlcRT5nbQ2_EsOWkDEmeD\/items\n1 > Accept: application\/json\n1 > Content-type: application\/json; charset=UTF-8\n1 > Content-Length: 31\n1 > Host: simple-grocery-store-api.online\n1 > Connection: Keep-Alive\n1 > User-Agent: Apache-HttpClient\/4.5.14 (Java\/11.0.22)\n1 > Accept-Encoding: gzip,deflate\n{\"productId\":4641,\"quantity\":1}\n\n00:48:03.635 response time in milliseconds: 668\n1 < 201\n1 < server: Fly\/d5207058 (2024-05-13)\n1 < fly-request-id: 01HXYV1C7WYZ4CM73XDVG6X5V9-bom\n1 < date: Wed, 15 May 2024 19:18:03 GMT\n1 < content-type: application\/json; charset=utf-8\n1 < x-powered-by: Express\n1 < etag: W\/\"23-zSawO3lH0Ep4zeG73\/5XEZuelbA\"\n1 < transfer-encoding: chunked\n1 < via: 1.1 fly.io\n{\"created\":true,\"itemId\":605886212}\n\n","line":38}},{"name":"status 201","result":{"duration":17800,"status":"passed"},"match":{"location":"karate","arguments":[]},"keyword":"> Then","line":39},{"name":"url 'http:\/\/simple-grocery-store-api.online'","result":{"duration":173901,"status":"passed"},"match":{"location":"karate","arguments":[]},"keyword":"> Given","line":4},{"name":"def File = Java.type('java.io.File')","result":{"duration":501000,"status":"passed"},"match":{"location":"karate","arguments":[]},"keyword":"> *","line":5},{"name":"def Scanner = Java.type('java.util.Scanner')","result":{"duration":532500,"status":"passed"},"match":{"location":"karate","arguments":[]},"keyword":"> *","line":6},{"name":"def path = 'C:\/Users\/HarshvardhanNigaveka\/eclipse-workspace\/Grocery_karateFramework\/target\/CartId.txt'","result":{"duration":205101,"status":"passed"},"match":{"location":"karate","arguments":[]},"keyword":"> *","line":7},{"name":"def file = new File(path)","result":{"duration":295700,"status":"passed"},"match":{"location":"karate","arguments":[]},"keyword":"> *","line":8},{"name":"def scanner = new Scanner(file)","result":{"duration":1603200,"status":"passed"},"match":{"location":"karate","arguments":[]},"keyword":"> *","line":9},{"name":"def cartId = scanner.useDelimiter('\\\\Z').next()","result":{"duration":823401,"status":"passed"},"match":{"location":"karate","arguments":[]},"keyword":"> *","line":10},{"name":"scanner.close()","result":{"duration":350401,"status":"passed"},"match":{"location":"karate","arguments":[]},"keyword":"> *","line":11},{"name":"path '\/carts\/' + cartId + '\/items'","result":{"duration":319701,"status":"passed"},"match":{"location":"karate","arguments":[]},"keyword":"> Given","line":35},{"name":"request { \"productId\": 2585, \"quantity\": 2 }","result":{"duration":183800,"status":"passed"},"match":{"location":"karate","arguments":[]},"keyword":"> And","line":36},{"name":"headers {Accept :\"application\/json\",Content-type : \"application\/json\"}","result":{"duration":85101,"status":"passed"},"match":{"location":"karate","arguments":[]},"keyword":"> And","line":37},{"name":"method POST","result":{"duration":675925201,"status":"passed"},"match":{"location":"karate","arguments":[]},"keyword":"> When","line":38,"doc_string":{"content_type":"","value":"00:48:03.648 request:\n1 > POST http:\/\/simple-grocery-store-api.online\/carts\/RlcRT5nbQ2_EsOWkDEmeD\/items\n1 > Accept: application\/json\n1 > Content-type: application\/json; charset=UTF-8\n1 > Content-Length: 31\n1 > Host: simple-grocery-store-api.online\n1 > Connection: Keep-Alive\n1 > User-Agent: Apache-HttpClient\/4.5.14 (Java\/11.0.22)\n1 > Accept-Encoding: gzip,deflate\n{\"productId\":2585,\"quantity\":2}\n\n00:48:04.321 response time in milliseconds: 672\n1 < 201\n1 < server: Fly\/d5207058 (2024-05-13)\n1 < fly-request-id: 01HXYV1CWX1VA8WXT722M81Q7T-bom\n1 < date: Wed, 15 May 2024 19:18:03 GMT\n1 < content-type: application\/json; charset=utf-8\n1 < x-powered-by: Express\n1 < etag: W\/\"23-qL8qmjPDDSUZJhmEabTxC5VyG+M\"\n1 < transfer-encoding: chunked\n1 < via: 1.1 fly.io\n{\"created\":true,\"itemId\":222668553}\n\n","line":38}},{"name":"status 201","result":{"duration":9500,"status":"passed"},"match":{"location":"karate","arguments":[]},"keyword":"> Then","line":39},{"name":"url 'http:\/\/simple-grocery-store-api.online'","result":{"duration":238399,"status":"passed"},"match":{"location":"karate","arguments":[]},"keyword":"> Given","line":4},{"name":"def File = Java.type('java.io.File')","result":{"duration":938000,"status":"passed"},"match":{"location":"karate","arguments":[]},"keyword":"> *","line":5},{"name":"def Scanner = Java.type('java.util.Scanner')","result":{"duration":572800,"status":"passed"},"match":{"location":"karate","arguments":[]},"keyword":"> *","line":6},{"name":"def path = 'C:\/Users\/HarshvardhanNigaveka\/eclipse-workspace\/Grocery_karateFramework\/target\/CartId.txt'","result":{"duration":403400,"status":"passed"},"match":{"location":"karate","arguments":[]},"keyword":"> *","line":7},{"name":"def file = new File(path)","result":{"duration":314000,"status":"passed"},"match":{"location":"karate","arguments":[]},"keyword":"> *","line":8},{"name":"def scanner = new Scanner(file)","result":{"duration":1196700,"status":"passed"},"match":{"location":"karate","arguments":[]},"keyword":"> *","line":9},{"name":"def cartId = scanner.useDelimiter('\\\\Z').next()","result":{"duration":675500,"status":"passed"},"match":{"location":"karate","arguments":[]},"keyword":"> *","line":10},{"name":"scanner.close()","result":{"duration":307600,"status":"passed"},"match":{"location":"karate","arguments":[]},"keyword":"> *","line":11},{"name":"path '\/carts\/' + cartId + '\/items'","result":{"duration":157401,"status":"passed"},"match":{"location":"karate","arguments":[]},"keyword":"> Given","line":35},{"name":"request { \"productId\": 8739, \"quantity\": 2 }","result":{"duration":180199,"status":"passed"},"match":{"location":"karate","arguments":[]},"keyword":"> And","line":36},{"name":"headers {Accept :\"application\/json\",Content-type : \"application\/json\"}","result":{"duration":102700,"status":"passed"},"match":{"location":"karate","arguments":[]},"keyword":"> And","line":37},{"name":"method POST","result":{"duration":633754001,"status":"passed"},"match":{"location":"karate","arguments":[]},"keyword":"> When","line":38,"doc_string":{"content_type":"","value":"00:48:04.336 request:\n1 > POST http:\/\/simple-grocery-store-api.online\/carts\/RlcRT5nbQ2_EsOWkDEmeD\/items\n1 > Accept: application\/json\n1 > Content-type: application\/json; charset=UTF-8\n1 > Content-Length: 31\n1 > Host: simple-grocery-store-api.online\n1 > Connection: Keep-Alive\n1 > User-Agent: Apache-HttpClient\/4.5.14 (Java\/11.0.22)\n1 > Accept-Encoding: gzip,deflate\n{\"productId\":8739,\"quantity\":2}\n\n00:48:04.967 response time in milliseconds: 630\n1 < 201\n1 < server: Fly\/d5207058 (2024-05-13)\n1 < fly-request-id: 01HXYV1DJDTK1PQ01SJ50SYJ0W-bom\n1 < date: Wed, 15 May 2024 19:18:04 GMT\n1 < content-type: application\/json; charset=utf-8\n1 < x-powered-by: Express\n1 < etag: W\/\"23-TnvnxlZ84fDMu5I18gUiB2Ea84U\"\n1 < transfer-encoding: chunked\n1 < via: 1.1 fly.io\n{\"created\":true,\"itemId\":805566957}\n\n","line":38}},{"name":"status 201","result":{"duration":7800,"status":"passed"},"match":{"location":"karate","arguments":[]},"keyword":"> Then","line":39},{"name":"call read(\"classpath:com\/api\/automation\/Cart\/getCartItems.feature\")","result":{"duration":411108200,"status":"passed"},"match":{"location":"karate","arguments":[]},"keyword":"And","line":16},{"name":"com\/api\/automation\/Cart\/getCartItems.feature","result":{"duration":0,"status":"passed"},"match":{"location":"karate","arguments":[]},"keyword":"","line":16},{"name":"url 'http:\/\/simple-grocery-store-api.online'","result":{"duration":183700,"status":"passed"},"match":{"location":"karate","arguments":[]},"keyword":"> Given","line":4},{"name":"def File = Java.type('java.io.File')","result":{"duration":686300,"status":"passed"},"match":{"location":"karate","arguments":[]},"keyword":"> *","line":5},{"name":"def Scanner = Java.type('java.util.Scanner')","result":{"duration":218900,"status":"passed"},"match":{"location":"karate","arguments":[]},"keyword":"> *","line":6},{"name":"def path = 'C:\/Users\/HarshvardhanNigaveka\/eclipse-workspace\/Grocery_karateFramework\/target\/CartId.txt'","result":{"duration":141999,"status":"passed"},"match":{"location":"karate","arguments":[]},"keyword":"> *","line":7},{"name":"def file = new File(path)","result":{"duration":335700,"status":"passed"},"match":{"location":"karate","arguments":[]},"keyword":"> *","line":8},{"name":"def scanner = new Scanner(file)","result":{"duration":1216101,"status":"passed"},"match":{"location":"karate","arguments":[]},"keyword":"> *","line":9},{"name":"def cartId = scanner.useDelimiter('\\\\Z').next()","result":{"duration":714900,"status":"passed"},"match":{"location":"karate","arguments":[]},"keyword":"> *","line":10},{"name":"path '\/carts\/'+cartId+'\/items'","result":{"duration":594900,"status":"passed"},"match":{"location":"karate","arguments":[]},"keyword":"> Given","line":13},{"name":"method get","result":{"duration":396912800,"status":"passed"},"match":{"location":"karate","arguments":[]},"keyword":"> When","line":14,"doc_string":{"content_type":"","value":"00:48:04.982 request:\n1 > GET http:\/\/simple-grocery-store-api.online\/carts\/RlcRT5nbQ2_EsOWkDEmeD\/items\n1 > Host: simple-grocery-store-api.online\n1 > Connection: Keep-Alive\n1 > User-Agent: Apache-HttpClient\/4.5.14 (Java\/11.0.22)\n1 > Accept-Encoding: gzip,deflate\n\n\n00:48:05.376 response time in milliseconds: 394\n1 < 200\n1 < server: Fly\/d5207058 (2024-05-13)\n1 < fly-request-id: 01HXYV1E6WFW07MB35JANEP9AY-bom\n1 < date: Wed, 15 May 2024 19:18:04 GMT\n1 < content-type: application\/json; charset=utf-8\n1 < x-powered-by: Express\n1 < etag: W\/\"8e-oambGKCSMOH2o2MJ8akENHIuVNI\"\n1 < transfer-encoding: chunked\n1 < via: 1.1 fly.io\n[{\"id\":605886212,\"productId\":4641,\"quantity\":1},{\"id\":222668553,\"productId\":2585,\"quantity\":2},{\"id\":805566957,\"productId\":8739,\"quantity\":2}]\n\n","line":14}},{"name":"status 200","result":{"duration":7801,"status":"passed"},"match":{"location":"karate","arguments":[]},"keyword":"> Then","line":15},{"name":"print response","result":{"duration":1538999,"status":"passed"},"match":{"location":"karate","arguments":[]},"keyword":"> And","line":16,"doc_string":{"content_type":"","value":"00:48:05.379 [print] [\n  {\n    \"id\": 605886212,\n    \"productId\": 4641,\n    \"quantity\": 1\n  },\n  {\n    \"id\": 222668553,\n    \"productId\": 2585,\n    \"quantity\": 2\n  },\n  {\n    \"id\": 805566957,\n    \"productId\": 8739,\n    \"quantity\": 2\n  }\n]\n \n","line":16}},{"name":"call read(\"classpath:com\/api\/automation\/Order\/createNewOrder.feature\")","result":{"duration":1026732800,"status":"passed"},"match":{"location":"karate","arguments":[]},"comments":["#And call read(\"classpath:com\/api\/automation\/cart\/modifyItem.feature\")","#And call read(\"classpath:com\/api\/automation\/cart\/replaceItem.feature\")","#And call read(\"classpath:com\/api\/automation\/cart\/deleteItem.feature\")","# ORDERS"],"keyword":"And","line":21},{"name":"com\/api\/automation\/Order\/createNewOrder.feature","result":{"duration":0,"status":"passed"},"match":{"location":"karate","arguments":[]},"keyword":"","line":21},{"name":"url 'http:\/\/simple-grocery-store-api.online'","result":{"duration":267700,"status":"passed"},"match":{"location":"karate","arguments":[]},"keyword":"> Given","line":4},{"name":"def File = Java.type('java.io.File')","result":{"duration":967800,"status":"passed"},"match":{"location":"karate","arguments":[]},"keyword":"> *","line":5},{"name":"def Scanner = Java.type('java.util.Scanner')","result":{"duration":564700,"status":"passed"},"match":{"location":"karate","arguments":[]},"keyword":"> *","line":6},{"name":"def path = 'C:\/Users\/HarshvardhanNigaveka\/eclipse-workspace\/Grocery_karateFramework\/target\/CartId.txt'","result":{"duration":236800,"status":"passed"},"match":{"location":"karate","arguments":[]},"keyword":"> *","line":7},{"name":"def file = new File(path)","result":{"duration":422699,"status":"passed"},"match":{"location":"karate","arguments":[]},"keyword":"> *","line":8},{"name":"def scanner = new Scanner(file)","result":{"duration":1866500,"status":"passed"},"match":{"location":"karate","arguments":[]},"keyword":"> *","line":9},{"name":"def cartId = scanner.useDelimiter('\\\\Z').next()","result":{"duration":689701,"status":"passed"},"match":{"location":"karate","arguments":[]},"keyword":"> *","line":10},{"name":"def path1 = 'C:\/Users\/HarshvardhanNigaveka\/eclipse-workspace\/Grocery_karateFramework\/target\/secure.txt'","result":{"duration":781099,"status":"passed"},"match":{"location":"karate","arguments":[]},"keyword":"> *","line":11},{"name":"def file1 = new File(path1)","result":{"duration":1691001,"status":"passed"},"match":{"location":"karate","arguments":[]},"keyword":"> *","line":12},{"name":"def scanner = new Scanner(file1)","result":{"duration":2766099,"status":"passed"},"match":{"location":"karate","arguments":[]},"keyword":"> *","line":13},{"name":"def token = scanner.useDelimiter('\\\\Z').next()","result":{"duration":703300,"status":"passed"},"match":{"location":"karate","arguments":[]},"keyword":"> *","line":14},{"name":"scanner.close()","result":{"duration":303599,"status":"passed"},"match":{"location":"karate","arguments":[]},"keyword":"> *","line":15},{"name":"path '\/orders'","result":{"duration":1200900,"status":"passed"},"match":{"location":"karate","arguments":[]},"keyword":"> Given","line":18},{"name":"request { cartId: \"#(cartId)\", customerName: \"Harry\" }","result":{"duration":788100,"status":"passed"},"match":{"location":"karate","arguments":[]},"keyword":"> And","line":19},{"name":"header Authorization = 'Bearer ' + token","result":{"duration":810300,"status":"passed"},"match":{"location":"karate","arguments":[]},"keyword":"> And","line":20},{"name":"method post","result":{"duration":998749400,"status":"passed"},"match":{"location":"karate","arguments":[]},"keyword":"> When","line":21,"doc_string":{"content_type":"","value":"00:48:05.404 request:\n1 > POST http:\/\/simple-grocery-store-api.online\/orders\n1 > Authorization: Bearer 0913e0c94fa7e49f61dc019aab3964196a60ef2ee34d1ffc71df6c625a5ccb07\n1 > Content-Type: application\/json; charset=UTF-8\n1 > Content-Length: 57\n1 > Host: simple-grocery-store-api.online\n1 > Connection: Keep-Alive\n1 > User-Agent: Apache-HttpClient\/4.5.14 (Java\/11.0.22)\n1 > Accept-Encoding: gzip,deflate\n{\"cartId\":\"RlcRT5nbQ2_EsOWkDEmeD\",\"customerName\":\"Harry\"}\n\n00:48:06.400 response time in milliseconds: 995\n1 < 201\n1 < server: Fly\/d5207058 (2024-05-13)\n1 < fly-request-id: 01HXYV1EKTF0W0RS3EM4P7XR23-bom\n1 < date: Wed, 15 May 2024 19:18:05 GMT\n1 < content-type: application\/json; charset=utf-8\n1 < x-powered-by: Express\n1 < etag: W\/\"32-wqO+iEOJw3GW\/XBGNY7hy97Gcs0\"\n1 < transfer-encoding: chunked\n1 < via: 1.1 fly.io\n{\"created\":true,\"orderId\":\"0iXvC898jov23t-gJdZSP\"}\n\n","line":21}},{"name":"status 201","result":{"duration":7300,"status":"passed"},"match":{"location":"karate","arguments":[]},"keyword":"> Then","line":22},{"name":"match response.created == true","result":{"duration":577900,"status":"passed"},"match":{"location":"karate","arguments":[]},"keyword":"> And","line":23},{"name":"def orderId = response.orderId","result":{"duration":1387200,"status":"passed"},"match":{"location":"karate","arguments":[]},"keyword":"> And","line":24},{"name":"karate.write(orderId, 'orderId.txt')","result":{"duration":3560201,"status":"passed"},"match":{"location":"karate","arguments":[]},"keyword":"> And","line":25,"doc_string":{"content_type":"","value":"00:48:06.405 write to file: target\\orderId.txt\n","line":25}},{"name":"call read(\"classpath:com\/api\/automation\/Order\/getAllOrders.feature\")","result":{"duration":509888599,"status":"passed"},"match":{"location":"karate","arguments":[]},"keyword":"And","line":22},{"name":"com\/api\/automation\/Order\/getAllOrders.feature","result":{"duration":0,"status":"passed"},"match":{"location":"karate","arguments":[]},"keyword":"","line":22},{"name":"url 'http:\/\/simple-grocery-store-api.online'","result":{"duration":211699,"status":"passed"},"match":{"location":"karate","arguments":[]},"keyword":"> Given","line":4},{"name":"def File = Java.type('java.io.File')","result":{"duration":869500,"status":"passed"},"match":{"location":"karate","arguments":[]},"keyword":"> *","line":5},{"name":"def Scanner = Java.type('java.util.Scanner')","result":{"duration":587700,"status":"passed"},"match":{"location":"karate","arguments":[]},"keyword":"> *","line":6},{"name":"def path = 'C:\/Users\/HarshvardhanNigaveka\/eclipse-workspace\/Grocery_karateFramework\/target\/secure.txt'","result":{"duration":291699,"status":"passed"},"match":{"location":"karate","arguments":[]},"keyword":"> *","line":7},{"name":"def file = new File(path)","result":{"duration":427800,"status":"passed"},"match":{"location":"karate","arguments":[]},"keyword":"> *","line":8},{"name":"def scanner = new Scanner(file)","result":{"duration":1140601,"status":"passed"},"match":{"location":"karate","arguments":[]},"keyword":"> *","line":9},{"name":"def token = scanner.useDelimiter('\\\\Z').next()","result":{"duration":10192500,"status":"passed"},"match":{"location":"karate","arguments":[]},"keyword":"> *","line":10},{"name":"scanner.close()","result":{"duration":759200,"status":"passed"},"match":{"location":"karate","arguments":[]},"keyword":"> *","line":11},{"name":"path '\/orders'","result":{"duration":153000,"status":"passed"},"match":{"location":"karate","arguments":[]},"keyword":"> Given","line":15},{"name":"header Authorization = 'Bearer ' + token","result":{"duration":331400,"status":"passed"},"match":{"location":"karate","arguments":[]},"keyword":"> And","line":16},{"name":"method get","result":{"duration":483329099,"status":"passed"},"match":{"location":"karate","arguments":[]},"keyword":"> When","line":17,"doc_string":{"content_type":"","value":"00:48:06.432 request:\n1 > GET http:\/\/simple-grocery-store-api.online\/orders\n1 > Authorization: Bearer 0913e0c94fa7e49f61dc019aab3964196a60ef2ee34d1ffc71df6c625a5ccb07\n1 > Host: simple-grocery-store-api.online\n1 > Connection: Keep-Alive\n1 > User-Agent: Apache-HttpClient\/4.5.14 (Java\/11.0.22)\n1 > Accept-Encoding: gzip,deflate\n\n\n00:48:06.913 response time in milliseconds: 480\n1 < 200\n1 < server: Fly\/d5207058 (2024-05-13)\n1 < fly-request-id: 01HXYV1FM08C6RD6GS3N53JKM6-bom\n1 < date: Wed, 15 May 2024 19:18:06 GMT\n1 < content-type: application\/json; charset=utf-8\n1 < x-powered-by: Express\n1 < etag: W\/\"377-5Uzgv2SKurHKYLdocUt4v1ukFsU\"\n1 < transfer-encoding: chunked\n1 < via: 1.1 fly.io\n[{\"id\":\"zSksD7LipO2FoWwB6F4IH\",\"items\":[{\"id\":742196879,\"productId\":4641,\"quantity\":1},{\"id\":163789608,\"productId\":8739,\"quantity\":2}],\"customerName\":\"Harry\",\"created\":\"2024-05-15T17:06:05.564Z\",\"comment\":\"\"},{\"id\":\"j6tfrcYlPaKeJWoc79_0N\",\"items\":[{\"id\":116766759,\"productId\":4641,\"quantity\":1},{\"id\":159830689,\"productId\":8739,\"quantity\":2}],\"customerName\":\"Harry\",\"created\":\"2024-05-15T17:13:17.074Z\",\"comment\":\"\"},{\"id\":\"lsC4v1QLoUcQ00oKOsvlZ\",\"items\":[{\"id\":763067286,\"productId\":4641,\"quantity\":1},{\"id\":769747167,\"productId\":8739,\"quantity\":2}],\"customerName\":\"Harry Nikola\",\"created\":\"2024-05-15T18:10:10.383Z\",\"comment\":\"\"},{\"id\":\"0iXvC898jov23t-gJdZSP\",\"items\":[{\"id\":605886212,\"productId\":4641,\"quantity\":1},{\"id\":222668553,\"productId\":2585,\"quantity\":2},{\"id\":805566957,\"productId\":8739,\"quantity\":2}],\"customerName\":\"Harry\",\"created\":\"2024-05-15T19:18:05.317Z\",\"comment\":\"\"}]\n\n","line":17}},{"name":"status 200","result":{"duration":8600,"status":"passed"},"match":{"location":"karate","arguments":[]},"keyword":"> Then","line":18},{"name":"print response","result":{"duration":1749900,"status":"passed"},"match":{"location":"karate","arguments":[]},"keyword":"> And","line":19,"doc_string":{"content_type":"","value":"00:48:06.916 [print] [\n  {\n    \"id\": \"zSksD7LipO2FoWwB6F4IH\",\n    \"items\": [\n      {\n        \"id\": 742196879,\n        \"productId\": 4641,\n        \"quantity\": 1\n      },\n      {\n        \"id\": 163789608,\n        \"productId\": 8739,\n        \"quantity\": 2\n      }\n    ],\n    \"customerName\": \"Harry\",\n    \"created\": \"2024-05-15T17:06:05.564Z\",\n    \"comment\": \"\"\n  },\n  {\n    \"id\": \"j6tfrcYlPaKeJWoc79_0N\",\n    \"items\": [\n      {\n        \"id\": 116766759,\n        \"productId\": 4641,\n        \"quantity\": 1\n      },\n      {\n        \"id\": 159830689,\n        \"productId\": 8739,\n        \"quantity\": 2\n      }\n    ],\n    \"customerName\": \"Harry\",\n    \"created\": \"2024-05-15T17:13:17.074Z\",\n    \"comment\": \"\"\n  },\n  {\n    \"id\": \"lsC4v1QLoUcQ00oKOsvlZ\",\n    \"items\": [\n      {\n        \"id\": 763067286,\n        \"productId\": 4641,\n        \"quantity\": 1\n      },\n      {\n        \"id\": 769747167,\n        \"productId\": 8739,\n        \"quantity\": 2\n      }\n    ],\n    \"customerName\": \"Harry Nikola\",\n    \"created\": \"2024-05-15T18:10:10.383Z\",\n    \"comment\": \"\"\n  },\n  {\n    \"id\": \"0iXvC898jov23t-gJdZSP\",\n    \"items\": [\n      {\n        \"id\": 605886212,\n        \"productId\": 4641,\n        \"quantity\": 1\n      },\n      {\n        \"id\": 222668553,\n        \"productId\": 2585,\n        \"quantity\": 2\n      },\n      {\n        \"id\": 805566957,\n        \"productId\": 8739,\n        \"quantity\": 2\n      }\n    ],\n    \"customerName\": \"Harry\",\n    \"created\": \"2024-05-15T19:18:05.317Z\",\n    \"comment\": \"\"\n  }\n]\n \n","line":19}},{"name":"call read(\"classpath:com\/api\/automation\/Order\/getSingleOrder.feature\")","result":{"duration":511011500,"status":"passed"},"match":{"location":"karate","arguments":[]},"keyword":"And","line":23},{"name":"com\/api\/automation\/Order\/getSingleOrder.feature","result":{"duration":0,"status":"passed"},"match":{"location":"karate","arguments":[]},"keyword":"","line":23},{"name":"url 'http:\/\/simple-grocery-store-api.online'","result":{"duration":202301,"status":"passed"},"match":{"location":"karate","arguments":[]},"keyword":"> Given","line":4},{"name":"def File = Java.type('java.io.File')","result":{"duration":808501,"status":"passed"},"match":{"location":"karate","arguments":[]},"keyword":"> *","line":5},{"name":"def Scanner = Java.type('java.util.Scanner')","result":{"duration":370300,"status":"passed"},"match":{"location":"karate","arguments":[]},"keyword":"> *","line":6},{"name":"def path = 'C:\/Users\/HarshvardhanNigaveka\/eclipse-workspace\/Grocery_karateFramework\/target\/secure.txt'","result":{"duration":180300,"status":"passed"},"match":{"location":"karate","arguments":[]},"keyword":"> *","line":7},{"name":"def file = new File(path)","result":{"duration":295900,"status":"passed"},"match":{"location":"karate","arguments":[]},"keyword":"> *","line":8},{"name":"def scanner = new Scanner(file)","result":{"duration":986400,"status":"passed"},"match":{"location":"karate","arguments":[]},"keyword":"> *","line":9},{"name":"def token = scanner.useDelimiter('\\\\Z').next()","result":{"duration":441401,"status":"passed"},"match":{"location":"karate","arguments":[]},"keyword":"> *","line":10},{"name":"def path1 = 'C:\/Users\/HarshvardhanNigaveka\/eclipse-workspace\/Grocery_karateFramework\/target\/orderId.txt'","result":{"duration":486001,"status":"passed"},"match":{"location":"karate","arguments":[]},"keyword":"> *","line":11},{"name":"def file1 = new File(path1)","result":{"duration":526400,"status":"passed"},"match":{"location":"karate","arguments":[]},"keyword":"> *","line":12},{"name":"def scanner = new Scanner(file1)","result":{"duration":870900,"status":"passed"},"match":{"location":"karate","arguments":[]},"keyword":"> *","line":13},{"name":"def orderId = scanner.useDelimiter('\\\\Z').next()","result":{"duration":502401,"status":"passed"},"match":{"location":"karate","arguments":[]},"keyword":"> *","line":14},{"name":"scanner.close()","result":{"duration":180700,"status":"passed"},"match":{"location":"karate","arguments":[]},"keyword":"> *","line":15},{"name":"path '\/orders\/'+ orderId","result":{"duration":967300,"status":"passed"},"match":{"location":"karate","arguments":[]},"keyword":"> Given","line":18},{"name":"print \"ORDER ID: \", orderId","result":{"duration":1078401,"status":"passed"},"match":{"location":"karate","arguments":[]},"keyword":"> *","line":19,"doc_string":{"content_type":"","value":"00:48:06.930 [print] ORDER ID:  0iXvC898jov23t-gJdZSP \n","line":19}},{"name":"header Authorization = 'Bearer ' + token","result":{"duration":227301,"status":"passed"},"match":{"location":"karate","arguments":[]},"keyword":"> And","line":20},{"name":"method get","result":{"duration":494347700,"status":"passed"},"match":{"location":"karate","arguments":[]},"keyword":"> When","line":21,"doc_string":{"content_type":"","value":"00:48:06.932 request:\n1 > GET http:\/\/simple-grocery-store-api.online\/orders\/0iXvC898jov23t-gJdZSP\n1 > Authorization: Bearer 0913e0c94fa7e49f61dc019aab3964196a60ef2ee34d1ffc71df6c625a5ccb07\n1 > Host: simple-grocery-store-api.online\n1 > Connection: Keep-Alive\n1 > User-Agent: Apache-HttpClient\/4.5.14 (Java\/11.0.22)\n1 > Accept-Encoding: gzip,deflate\n\n\n00:48:07.424 response time in milliseconds: 492\n1 < 200\n1 < server: Fly\/d5207058 (2024-05-13)\n1 < fly-request-id: 01HXYV1G3GHAC2BQH1ADPMFQMG-bom\n1 < date: Wed, 15 May 2024 19:18:06 GMT\n1 < content-type: application\/json; charset=utf-8\n1 < x-powered-by: Express\n1 < etag: W\/\"179-9agL6wIcxqQtFwyNTWpTSEiS3Iw\"\n1 < transfer-encoding: chunked\n1 < via: 1.1 fly.io\n{\"id\":\"0iXvC898jov23t-gJdZSP\",\"items\":[{\"id\":605886212,\"productId\":4641,\"quantity\":1},{\"id\":222668553,\"productId\":2585,\"quantity\":2},{\"id\":805566957,\"productId\":8739,\"quantity\":2}],\"customerName\":\"Harry\",\"createdBy\":\"d563ccc780e4397ab162a9d56d0ecabe2ca5d6e2be7bb263ecf271e4e63e2db2\",\"created\":\"2024-05-15T19:18:05.317Z\",\"timestamp\":1715800685318,\"processed\":false,\"comment\":\"\"}\n\n","line":21}},{"name":"status 200","result":{"duration":9999,"status":"passed"},"match":{"location":"karate","arguments":[]},"keyword":"> Then","line":22},{"name":"print response","result":{"duration":1001600,"status":"passed"},"match":{"location":"karate","arguments":[]},"keyword":"> And","line":23,"doc_string":{"content_type":"","value":"00:48:07.426 [print] {\n  \"id\": \"0iXvC898jov23t-gJdZSP\",\n  \"items\": [\n    {\n      \"id\": 605886212,\n      \"productId\": 4641,\n      \"quantity\": 1\n    },\n    {\n      \"id\": 222668553,\n      \"productId\": 2585,\n      \"quantity\": 2\n    },\n    {\n      \"id\": 805566957,\n      \"productId\": 8739,\n      \"quantity\": 2\n    }\n  ],\n  \"customerName\": \"Harry\",\n  \"createdBy\": \"d563ccc780e4397ab162a9d56d0ecabe2ca5d6e2be7bb263ecf271e4e63e2db2\",\n  \"created\": \"2024-05-15T19:18:05.317Z\",\n  \"timestamp\": 1715800685318,\n  \"processed\": false,\n  \"comment\": \"\"\n}\n \n","line":23}},{"name":"call read(\"classpath:com\/api\/automation\/Order\/updateOrder.feature\")","result":{"duration":817433700,"status":"passed"},"match":{"location":"karate","arguments":[]},"keyword":"And","line":24},{"name":"com\/api\/automation\/Order\/updateOrder.feature","result":{"duration":0,"status":"passed"},"match":{"location":"karate","arguments":[]},"keyword":"","line":24},{"name":"url 'http:\/\/simple-grocery-store-api.online'","result":{"duration":233801,"status":"passed"},"match":{"location":"karate","arguments":[]},"keyword":"> Given","line":4},{"name":"def File = Java.type('java.io.File')","result":{"duration":775800,"status":"passed"},"match":{"location":"karate","arguments":[]},"keyword":"> *","line":5},{"name":"def Scanner = Java.type('java.util.Scanner')","result":{"duration":515500,"status":"passed"},"match":{"location":"karate","arguments":[]},"keyword":"> *","line":6},{"name":"def path = 'C:\/Users\/HarshvardhanNigaveka\/eclipse-workspace\/Grocery_karateFramework\/target\/secure.txt'","result":{"duration":250500,"status":"passed"},"match":{"location":"karate","arguments":[]},"keyword":"> *","line":7},{"name":"def file = new File(path)","result":{"duration":498700,"status":"passed"},"match":{"location":"karate","arguments":[]},"keyword":"> *","line":8},{"name":"def scanner = new Scanner(file)","result":{"duration":1110200,"status":"passed"},"match":{"location":"karate","arguments":[]},"keyword":"> *","line":9},{"name":"def token = scanner.useDelimiter('\\\\Z').next()","result":{"duration":737200,"status":"passed"},"match":{"location":"karate","arguments":[]},"keyword":"> *","line":10},{"name":"def path1 = 'C:\/Users\/HarshvardhanNigaveka\/eclipse-workspace\/Grocery_karateFramework\/target\/orderId.txt'","result":{"duration":363599,"status":"passed"},"match":{"location":"karate","arguments":[]},"keyword":"> *","line":11},{"name":"def file1 = new File(path1)","result":{"duration":433000,"status":"passed"},"match":{"location":"karate","arguments":[]},"keyword":"> *","line":12},{"name":"def scanner = new Scanner(file1)","result":{"duration":1324299,"status":"passed"},"match":{"location":"karate","arguments":[]},"keyword":"> *","line":13},{"name":"def orderId = scanner.useDelimiter('\\\\Z').next()","result":{"duration":1092400,"status":"passed"},"match":{"location":"karate","arguments":[]},"keyword":"> *","line":14},{"name":"scanner.close()","result":{"duration":248400,"status":"passed"},"match":{"location":"karate","arguments":[]},"keyword":"> *","line":15},{"name":"path '\/orders\/'+ orderId","result":{"duration":505700,"status":"passed"},"match":{"location":"karate","arguments":[]},"keyword":"> Given","line":18},{"name":"print \"ORDER ID: \", orderId","result":{"duration":521300,"status":"passed"},"match":{"location":"karate","arguments":[]},"keyword":"> *","line":19,"doc_string":{"content_type":"","value":"00:48:07.445 [print] ORDER ID:  0iXvC898jov23t-gJdZSP \n","line":19}},{"name":"header Authorization = 'Bearer ' + token","result":{"duration":204200,"status":"passed"},"match":{"location":"karate","arguments":[]},"keyword":"> And","line":20},{"name":"request {customerName:'Harry Nikola'}","result":{"duration":117200,"status":"passed"},"match":{"location":"karate","arguments":[]},"keyword":"> And","line":21},{"name":"method patch","result":{"duration":797316201,"status":"passed"},"match":{"location":"karate","arguments":[]},"keyword":"> When","line":22,"doc_string":{"content_type":"","value":"00:48:07.448 request:\n1 > PATCH http:\/\/simple-grocery-store-api.online\/orders\/0iXvC898jov23t-gJdZSP\n1 > Authorization: Bearer 0913e0c94fa7e49f61dc019aab3964196a60ef2ee34d1ffc71df6c625a5ccb07\n1 > Content-Type: application\/json; charset=UTF-8\n1 > Content-Length: 31\n1 > Host: simple-grocery-store-api.online\n1 > Connection: Keep-Alive\n1 > User-Agent: Apache-HttpClient\/4.5.14 (Java\/11.0.22)\n1 > Accept-Encoding: gzip,deflate\n{\"customerName\":\"Harry Nikola\"}\n\n00:48:08.242 response time in milliseconds: 794\n1 < 204\n1 < server: Fly\/d5207058 (2024-05-13)\n1 < fly-request-id: 01HXYV1GKK57QANVWCCPEYZ1RE-bom\n1 < date: Wed, 15 May 2024 19:18:07 GMT\n1 < x-powered-by: Express\n1 < via: 1.1 fly.io\n\n\n","line":22}},{"name":"status 204","result":{"duration":9000,"status":"passed"},"match":{"location":"karate","arguments":[]},"keyword":"> Then","line":23},{"name":"print response","result":{"duration":879200,"status":"passed"},"match":{"location":"karate","arguments":[]},"keyword":"> And","line":24,"doc_string":{"content_type":"","value":"00:48:08.244 [print]  \n","line":24}},{"name":"call read(\"classpath:com\/api\/automation\/Order\/deleteOrder.feature\")","result":{"duration":819719299,"status":"passed"},"match":{"location":"karate","arguments":[]},"keyword":"And","line":25},{"name":"com\/api\/automation\/Order\/deleteOrder.feature","result":{"duration":0,"status":"passed"},"match":{"location":"karate","arguments":[]},"keyword":"","line":25},{"name":"url 'http:\/\/simple-grocery-store-api.online'","result":{"duration":151199,"status":"passed"},"match":{"location":"karate","arguments":[]},"keyword":"> Given","line":4},{"name":"def File = Java.type('java.io.File')","result":{"duration":1167200,"status":"passed"},"match":{"location":"karate","arguments":[]},"keyword":"> *","line":5},{"name":"def Scanner = Java.type('java.util.Scanner')","result":{"duration":608001,"status":"passed"},"match":{"location":"karate","arguments":[]},"keyword":"> *","line":6},{"name":"def path = 'C:\/Users\/HarshvardhanNigaveka\/eclipse-workspace\/Grocery_karateFramework\/target\/secure.txt'","result":{"duration":218500,"status":"passed"},"match":{"location":"karate","arguments":[]},"keyword":"> *","line":7},{"name":"def file = new File(path)","result":{"duration":369500,"status":"passed"},"match":{"location":"karate","arguments":[]},"keyword":"> *","line":8},{"name":"def scanner = new Scanner(file)","result":{"duration":1029800,"status":"passed"},"match":{"location":"karate","arguments":[]},"keyword":"> *","line":9},{"name":"def token = scanner.useDelimiter('\\\\Z').next()","result":{"duration":1015500,"status":"passed"},"match":{"location":"karate","arguments":[]},"keyword":"> *","line":10},{"name":"def path1 = 'C:\/Users\/HarshvardhanNigaveka\/eclipse-workspace\/Grocery_karateFramework\/target\/orderId.txt'","result":{"duration":280000,"status":"passed"},"match":{"location":"karate","arguments":[]},"keyword":"> *","line":11},{"name":"def file1 = new File(path1)","result":{"duration":317500,"status":"passed"},"match":{"location":"karate","arguments":[]},"keyword":"> *","line":12},{"name":"def scanner = new Scanner(file1)","result":{"duration":707901,"status":"passed"},"match":{"location":"karate","arguments":[]},"keyword":"> *","line":13},{"name":"def orderId = scanner.useDelimiter('\\\\Z').next()","result":{"duration":394300,"status":"passed"},"match":{"location":"karate","arguments":[]},"keyword":"> *","line":14},{"name":"scanner.close()","result":{"duration":131901,"status":"passed"},"match":{"location":"karate","arguments":[]},"keyword":"> *","line":15},{"name":"path '\/orders\/'+ orderId","result":{"duration":91800,"status":"passed"},"match":{"location":"karate","arguments":[]},"keyword":"> Given","line":18},{"name":"print \"ORDER ID: \", orderId","result":{"duration":239800,"status":"passed"},"match":{"location":"karate","arguments":[]},"keyword":"> *","line":19,"doc_string":{"content_type":"","value":"00:48:08.258 [print] ORDER ID:  0iXvC898jov23t-gJdZSP \n","line":19}},{"name":"header Authorization = 'Bearer ' + token","result":{"duration":112000,"status":"passed"},"match":{"location":"karate","arguments":[]},"keyword":"> And","line":20},{"name":"method delete","result":{"duration":803648000,"status":"passed"},"match":{"location":"karate","arguments":[]},"keyword":"> When","line":21,"doc_string":{"content_type":"","value":"00:48:08.261 request:\n1 > DELETE http:\/\/simple-grocery-store-api.online\/orders\/0iXvC898jov23t-gJdZSP\n1 > Authorization: Bearer 0913e0c94fa7e49f61dc019aab3964196a60ef2ee34d1ffc71df6c625a5ccb07\n1 > Host: simple-grocery-store-api.online\n1 > Connection: Keep-Alive\n1 > User-Agent: Apache-HttpClient\/4.5.14 (Java\/11.0.22)\n1 > Accept-Encoding: gzip,deflate\n\n\n00:48:09.062 response time in milliseconds: 800\n1 < 204\n1 < server: Fly\/d5207058 (2024-05-13)\n1 < fly-request-id: 01HXYV1HD043WD8QN7ZQX9GVQ0-bom\n1 < date: Wed, 15 May 2024 19:18:08 GMT\n1 < x-powered-by: Express\n1 < via: 1.1 fly.io\n\n\n","line":21}},{"name":"status 204","result":{"duration":9000,"status":"passed"},"match":{"location":"karate","arguments":[]},"keyword":"> Then","line":22},{"name":"print response","result":{"duration":1645900,"status":"passed"},"match":{"location":"karate","arguments":[]},"keyword":"> And","line":23,"doc_string":{"content_type":"","value":"00:48:09.064 [print]  \n","line":23}}],"tags":[]}],"name":"com\/api\/automation\/master.feature","description":"To automate the tests","id":"to-automate-the-tests","keyword":"Feature","uri":"com\/api\/automation\/master.feature"}]